{"nodes": [{"id": "community_getting_started", "label": "Getting Started (Community)", "file_type": "community", "source_file": "graphify-out/obsidian/_COMMUNITY_Getting Started.md", "source_location": null, "source_url": null, "captured_at": null, "author": null, "contributor": null}], "edges": [{"source": "community_getting_started", "target": "blog_hello_world", "relation": "has_member", "confidence": "EXTRACTED", "confidence_score": 1.0, "source_file": "graphify-out/obsidian/_COMMUNITY_Getting Started.md", "source_location": null, "weight": 1.0}, {"source": "community_getting_started", "target": "raw_readme_wiki_source_guide", "relation": "has_member", "confidence": "EXTRACTED", "confidence_score": 1.0, "source_file": "graphify-out/obsidian/_COMMUNITY_Getting Started.md", "source_location": null, "weight": 1.0}, {"source": "community_getting_started", "target": "wiki_getting_started", "relation": "has_member", "confidence": "EXTRACTED", "confidence_score": 1.0, "source_file": "graphify-out/obsidian/_COMMUNITY_Getting Started.md", "source_location": null, "weight": 1.0}], "hyperedges": []}